tfwsdk/__init__.py
tfwsdk/sdk.py
tfwsdk/zmq_connector.py
tfwsdk-1.0.2.dist-info/LICENSE
tfwsdk-1.0.2.dist-info/METADATA
tfwsdk-1.0.2.dist-info/WHEEL
tfwsdk-1.0.2.dist-info/top_level.txt
tfwsdk-1.0.2.dist-info/RECORD
