Metadata-Version: 2.1
Name: tfwsdk
Version: 1.0.2
Summary: Python SDK for our Tutorial Framework
Home-page: https://github.com/avatao-content/tfwsdk-python
Author: Avatao.com Innovative Learning Kft.
Author-email: support@avatao.com
License: Apache License 2.0
Platform: UNKNOWN
Classifier: Programming Language :: Python :: 3
Classifier: License :: OSI Approved :: Apache Software License
Classifier: Operating System :: OS Independent
Requires-Dist: pyzmq (>=19.0.2)
Requires-Dist: tornado (>=6.0.4)
